synmod/__init__.py
synmod/__main__.py
synmod/aggregators.py
synmod/constants.py
synmod/features.py
synmod/generators.py
synmod/master.py
synmod/models.py
synmod/utils.py
tests/__init__.py
tests/conftest.py
tests/test_master.py
tests/utils.py
tests/test_master/test_reproducible_classifier.yml
tests/test_master/test_reproducible_regressor.yml
tests/test_master/test_reproducible_standardize_features.json
tests/test_master/test_reproducible_standardize_features.yml
tests/test_master/test_reproducible_write_outputs.json
tests/test_master/test_reproducible_write_outputs.yml
synmod-0.1.4.dist-info/LICENSE
synmod-0.1.4.dist-info/METADATA
synmod-0.1.4.dist-info/WHEEL
synmod-0.1.4.dist-info/entry_points.txt
synmod-0.1.4.dist-info/top_level.txt
synmod-0.1.4.dist-info/zip-safe
synmod-0.1.4.dist-info/RECORD
